driveline/__init__.py
driveline/consumers.py
driveline/exceptions.py
driveline/id_factory.py
driveline/opts.py
driveline/record_data.py
driveline/sync.py
driveline/video.py
driveline-0.14.1.dist-info/LICENSE
driveline-0.14.1.dist-info/METADATA
driveline-0.14.1.dist-info/WHEEL
driveline-0.14.1.dist-info/top_level.txt
driveline-0.14.1.dist-info/RECORD
