Metadata-Version: 2.1
Name: driveline
Version: 0.14.1
Summary: Driveline client
Home-page: https://github.com/1533-systems/python3-sdk
Author: 1533 Systems
Author-email: info@1533.io
License: MIT
Keywords: driveline performance database streaming document
Platform: UNKNOWN
Classifier: License :: OSI Approved :: MIT License
Classifier: Programming Language :: Python :: 3
Classifier: Programming Language :: Python :: 3.6
Classifier: Programming Language :: Python :: 3.7
Classifier: Operating System :: OS Independent
Requires-Python: >=3.6.0
Requires-Dist: websockets (~=7.0)
Requires-Dist: cbor (~=1.0)
